aiostore/__init__.py
aiostore/base.py
aiostore/eager_scandir.py
aiostore/filesystem.py
aiostore/minio.py
aiostore-0.1.0.dist-info/WHEEL
aiostore-0.1.0.dist-info/METADATA
aiostore-0.1.0.dist-info/RECORD
